{
  "hits": [
    {
      "first_name": "Shelley Rosenbaum",
      "last_name": "Kassulke",
      "email": "Clinton_Oberbrunner93@yahoo.com",
      "address": "78123 Lavada Port",
      "phoneNumber": "221978598"
    },
    {
      "first_name": "Luke Cronin",
      "last_name": "Sauer",
      "email": "Shemar.Fisher@gmail.com",
      "address": "8009 Wilfrid Haven",
      "phoneNumber": "788481102"
    },
    {
      "first_name": "Bill Tillman",
      "last_name": "Leffler",
      "email": "Orville95@yahoo.com",
      "address": "0799 Schoen Locks",
      "phoneNumber": "467257704"
    }
  ]
}